Workbook

Sheet Setup
A1: Guarantor | B1: Include?
A2: Guarantor1 | B2: TRUE
A3: Guarantor2 | B3: TRUE
A4: Guarantor3 | B4: FALSE
A5: Guarantor4 | B5: FALSE
A6: Guarantor5 | B6: FALSE

Sheet Guarantor1_Data
A1: Entity | B1: Guarantor | C1: Revenue | D1: Income | E1: Interest | F1: Depreciation | G1: Addbacks | H1: CapEx | I1: NOI | J1: Total Annual Debt Service | K1: CF After Debt Service | L1: DSCR | M1: Committed Debt | N1: Recourse | O1: Ownership | P1: Guarantor NOI | Q1: Guarantor Annual Debt Service | R1: Guarantor CF After Debt Service | S1: Guarantor Debt Recourse | T1: Other Interest | U1: Amortization | V1: Distributions | W1: Total Pymt/Mo | X1: Guarantor Net Income | Y1: Rate Shock DSCR | AA1: Annual Rate Shock | AB1: Notes | AC1: Debt 1 | AD1: Am | AE1: Type 1 | AF1: Rate 1 | AG1: Pymt/Mo 1 | AH1: Pymt/Mo Over 1 | AI1: Annual Debt 1 | AJ1: Debt 2 | AK1: Am 2 | AL1: Type 2 | AM1: Rate 2 | AN1: Pymt/Month 2 | AO1: Pymt/Mo Override 2
B2: ='Setup'!A2

Sheet Guarantor2_Data
A1: Entity | B1: Guarantor | C1: Revenue | D1: Income | E1: Interest | F1: Depreciation | G1: Addbacks | H1: CapEx | I1: NOI | J1: Total Annual Debt Service | K1: CF After Debt Service | L1: DSCR | M1: Committed Debt | N1: Recourse | O1: Ownership | P1: Guarantor NOI | Q1: Guarantor Annual Debt Service | R1: Guarantor CF After Debt Service | S1: Guarantor Debt Recourse | T1: Other Interest | U1: Amortization | V1: Distributions | W1: Total Pymt/Mo | X1: Guarantor Net Income | Y1: Rate Shock DSCR | AA1: Annual Rate Shock | AB1: Notes | AC1: Debt 1 | AD1: Am | AE1: Type 1 | AF1: Rate 1 | AG1: Pymt/Mo 1 | AH1: Pymt/Mo Over 1 | AI1: Annual Debt 1 | AJ1: Debt 2 | AK1: Am 2 | AL1: Type 2 | AM1: Rate 2 | AN1: Pymt/Month 2 | AO1: Pymt/Mo Override 2
B2: ='Setup'!A3

Sheet Guarantor3_Data
A1: Entity | B1: Guarantor | C1: Revenue | D1: Income | E1: Interest | F1: Depreciation | G1: Addbacks | H1: CapEx | I1: NOI | J1: Total Annual Debt Service | K1: CF After Debt Service | L1: DSCR | M1: Committed Debt | N1: Recourse | O1: Ownership | P1: Guarantor NOI | Q1: Guarantor Annual Debt Service | R1: Guarantor CF After Debt Service | S1: Guarantor Debt Recourse | T1: Other Interest | U1: Amortization | V1: Distributions | W1: Total Pymt/Mo | X1: Guarantor Net Income | Y1: Rate Shock DSCR | AA1: Annual Rate Shock | AB1: Notes | AC1: Debt 1 | AD1: Am | AE1: Type 1 | AF1: Rate 1 | AG1: Pymt/Mo 1 | AH1: Pymt/Mo Over 1 | AI1: Annual Debt 1 | AJ1: Debt 2 | AK1: Am 2 | AL1: Type 2 | AM1: Rate 2 | AN1: Pymt/Month 2 | AO1: Pymt/Mo Override 2
B2: ='Setup'!A4

Sheet Guarantor4_Data
A1: Entity | B1: Guarantor | C1: Revenue | D1: Income | E1: Interest | F1: Depreciation | G1: Addbacks | H1: CapEx | I1: NOI | J1: Total Annual Debt Service | K1: CF After Debt Service | L1: DSCR | M1: Committed Debt | N1: Recourse | O1: Ownership | P1: Guarantor NOI | Q1: Guarantor Annual Debt Service | R1: Guarantor CF After Debt Service | S1: Guarantor Debt Recourse | T1: Other Interest | U1: Amortization | V1: Distributions | W1: Total Pymt/Mo | X1: Guarantor Net Income | Y1: Rate Shock DSCR | AA1: Annual Rate Shock | AB1: Notes | AC1: Debt 1 | AD1: Am | AE1: Type 1 | AF1: Rate 1 | AG1: Pymt/Mo 1 | AH1: Pymt/Mo Over 1 | AI1: Annual Debt 1 | AJ1: Debt 2 | AK1: Am 2 | AL1: Type 2 | AM1: Rate 2 | AN1: Pymt/Month 2 | AO1: Pymt/Mo Override 2
B2: ='Setup'!A5

Sheet Guarantor5_Data
A1: Entity | B1: Guarantor | C1: Revenue | D1: Income | E1: Interest | F1: Depreciation | G1: Addbacks | H1: CapEx | I1: NOI | J1: Total Annual Debt Service | K1: CF After Debt Service | L1: DSCR | M1: Committed Debt | N1: Recourse | O1: Ownership | P1: Guarantor NOI | Q1: Guarantor Annual Debt Service | R1: Guarantor CF After Debt Service | S1: Guarantor Debt Recourse | T1: Other Interest | U1: Amortization | V1: Distributions | W1: Total Pymt/Mo | X1: Guarantor Net Income | Y1: Rate Shock DSCR | AA1: Annual Rate Shock | AB1: Notes | AC1: Debt 1 | AD1: Am | AE1: Type 1 | AF1: Rate 1 | AG1: Pymt/Mo 1 | AH1: Pymt/Mo Over 1 | AI1: Annual Debt 1 | AJ1: Debt 2 | AK1: Am 2 | AL1: Type 2 | AM1: Rate 2 | AN1: Pymt/Month 2 | AO1: Pymt/Mo Override 2
B2: ='Setup'!A6

Sheet Master_Entities
A1: Entity | B1: Average NOI | C1: Average DSCR
A2: =UNIQUE(FILTER(VSTACK(IF(Setup!$B$1, Guarantor1_Data!$A$2:$A$1048576, ""),IF(Setup!$B$2, Guarantor2_Data!$A$2:$A$1048576, ""),IF(Setup!$B$3, Guarantor3_Data!$A$2:$A$1048576, ""),IF(Setup!$B$4, Guarantor4_Data!$A$2:$A$1048576, ""),IF(Setup!$B$5, Guarantor5_Data!$A$2:$A$1048576, "")), VSTACK(IF(Setup!$B$1, Guarantor1_Data!$A$2:$A$1048576<>"", ""),IF(Setup!$B$2, Guarantor2_Data!$A$2:$A$1048576<>"", ""),IF(Setup!$B$3, Guarantor3_Data!$A$2:$A$1048576<>"", ""),IF(Setup!$B$4, Guarantor4_Data!$A$2:$A$1048576<>"", ""),IF(Setup!$B$5, Guarantor5_Data!$A$2:$A$1048576<>"", "")))) | B2: =IF(A2="","", AVERAGEIFS(VSTACK(IF(Setup!$B$1, Guarantor1_Data!I:I, ""),IF(Setup!$B$2, Guarantor2_Data!I:I, ""),IF(Setup!$B$3, Guarantor3_Data!I:I, ""),IF(Setup!$B$4, Guarantor4_Data!I:I, ""),IF(Setup!$B$5, Guarantor5_Data!I:I, "")), VSTACK(IF(Setup!$B$1, Guarantor1_Data!$A$2:$A$1048576, ""),IF(Setup!$B$2, Guarantor2_Data!$A$2:$A$1048576, ""),IF(Setup!$B$3, Guarantor3_Data!$A$2:$A$1048576, ""),IF(Setup!$B$4, Guarantor4_Data!$A$2:$A$1048576, ""),IF(Setup!$B$5, Guarantor5_Data!$A$2:$A$1048576, "")), A2)) | C2: =IF(A2="","", AVERAGEIFS(VSTACK(IF(Setup!$B$1, Guarantor1_Data!L:L, ""),IF(Setup!$B$2, Guarantor2_Data!L:L, ""),IF(Setup!$B$3, Guarantor3_Data!L:L, ""),IF(Setup!$B$4, Guarantor4_Data!L:L, ""),IF(Setup!$B$5, Guarantor5_Data!L:L, "")), VSTACK(IF(Setup!$B$1, Guarantor1_Data!$A$2:$A$1048576, ""),IF(Setup!$B$2, Guarantor2_Data!$A$2:$A$1048576, ""),IF(Setup!$B$3, Guarantor3_Data!$A$2:$A$1048576, ""),IF(Setup!$B$4, Guarantor4_Data!$A$2:$A$1048576, ""),IF(Setup!$B$5, Guarantor5_Data!$A$2:$A$1048576, "")), A2))

Sheet Dashboard
A1: Guarantor Comparison Dashboard | B1: Select Guarantor 2 | I1: Instructions:
I2: 1. Select two guarantors from dropdowns in A2 and B2.
I3: 2. Paste raw data into the respective GuarantorX_Data sheets (Entity in column A).
A4: Entity | B4: G1 NOI | C4: G1 DSCR | D4: G2 NOI | E4: G2 DSCR | F4: NOI Variance | G4: DSCR Variance | I4: 3. Variances > 0.01 will be highlighted after you add conditional formatting (see below).
A5: =Master_Entities!A2# | F5: =IF(OR(B5="N/A",D5="N/A"),"N/A",ABS(B5-D5)) | G5: =IF(OR(C5="N/A",E5="N/A"),"N/A",ABS(C5-E5))
F6: =IF(OR(B5="N/A",D5="N/A"),"N/A",ABS(B5-D5)) | G6: =IF(OR(C5="N/A",E5="N/A"),"N/A",ABS(C5-E5)) | I6: Add Conditional Formatting:
F7: =IF(OR(B5="N/A",D5="N/A"),"N/A",ABS(B5-D5)) | G7: =IF(OR(C5="N/A",E5="N/A"),"N/A",ABS(C5-E5)) | I7: - Select F5:F504 > Home > Conditional Formatting > Greater Than > 0.01 > Red Fill
F8: =IF(OR(B5="N/A",D5="N/A"),"N/A",ABS(B5-D5)) | G8: =IF(OR(C5="N/A",E5="N/A"),"N/A",ABS(C5-E5)) | I8: - Repeat for G5:G504
F9: =IF(OR(B5="N/A",D5="N/A"),"N/A",ABS(B5-D5)) | G9: =IF(OR(C5="N/A",E5="N/A"),"N/A",ABS(C5-E5))
F10: =IF(OR(B5="N/A",D5="N/A"),"N/A",ABS(B5-D5)) | G10: =IF(OR(C5="N/A",E5="N/A"),"N/A",ABS(C5-E5))
F11: =IF(OR(B5="N/A",D5="N/A"),"N/A",ABS(B5-D5)) | G11: =IF(OR(C5="N/A",E5="N/A"),"N/A",ABS(C5-E5))
F12: =IF(OR(B5="N/A",D5="N/A"),"N/A",ABS(B5-D5)) | G12: =IF(OR(C5="N/A",E5="N/A"),"N/A",ABS(C5-E5))
F13: =IF(OR(B5="N/A",D5="N/A"),"N/A",ABS(B5-D5)) | G13: =IF(OR(C5="N/A",E5="N/A"),"N/A",ABS(C5-E5))
F14: =IF(OR(B5="N/A",D5="N/A"),"N/A",ABS(B5-D5)) | G14: =IF(OR(C5="N/A",E5="N/A"),"N/A",ABS(C5-E5))
F15: =IF(OR(B5="N/A",D5="N/A"),"N/A",ABS(B5-D5)) | G15: =IF(OR(C5="N/A",E5="N/A"),"N/A",ABS(C5-E5))
F16: =IF(OR(B5="N/A",D5="N/A"),"N/A",ABS(B5-D5)) | G16: =IF(OR(C5="N/A",E5="N/A"),"N/A",ABS(C5-E5))
F17: =IF(OR(B5="N/A",D5="N/A"),"N/A",ABS(B5-D5)) | G17: =IF(OR(C5="N/A",E5="N/A"),"N/A",ABS(C5-E5))
F18: =IF(OR(B5="N/A",D5="N/A"),"N/A",ABS(B5-D5)) | G18: =IF(OR(C5="N/A",E5="N/A"),"N/A",ABS(C5-E5))
F19: =IF(OR(B5="N/A",D5="N/A"),"N/A",ABS(B5-D5)) | G19: =IF(OR(C5="N/A",E5="N/A"),"N/A",ABS(C5-E5))
F20: =IF(OR(B5="N/A",D5="N/A"),"N/A",ABS(B5-D5)) | G20: =IF(OR(C5="N/A",E5="N/A"),"N/A",ABS(C5-E5))
F21: =IF(OR(B5="N/A",D5="N/A"),"N/A",ABS(B5-D5)) | G21: =IF(OR(C5="N/A",E5="N/A"),"N/A",ABS(C5-E5))
F22: =IF(OR(B5="N/A",D5="N/A"),"N/A",ABS(B5-D5)) | G22: =IF(OR(C5="N/A",E5="N/A"),"N/A",ABS(C5-E5))
F23: =IF(OR(B5="N/A",D5="N/A"),"N/A",ABS(B5-D5)) | G23: =IF(OR(C5="N/A",E5="N/A"),"N/A",ABS(C5-E5))
F24: =IF(OR(B5="N/A",D5="N/A"),"N/A",ABS(B5-D5)) | G24: =IF(OR(C5="N/A",E5="N/A"),"N/A",ABS(C5-E5))
F25: =IF(OR(B5="N/A",D5="N/A"),"N/A",ABS(B5-D5)) | G25: =IF(OR(C5="N/A",E5="N/A"),"N/A",ABS(C5-E5))
F26: =IF(OR(B5="N/A",D5="N/A"),"N/A",ABS(B5-D5)) | G26: =IF(OR(C5="N/A",E5="N/A"),"N/A",ABS(C5-E5))
F27: =IF(OR(B5="N/A",D5="N/A"),"N/A",ABS(B5-D5)) | G27: =IF(OR(C5="N/A",E5="N/A"),"N/A",ABS(C5-E5))
F28: =IF(OR(B5="N/A",D5="N/A"),"N/A",ABS(B5-D5)) | G28: =IF(OR(C5="N/A",E5="N/A"),"N/A",ABS(C5-E5))
F29: =IF(OR(B5="N/A",D5="N/A"),"N/A",ABS(B5-D5)) | G29: =IF(OR(C5="N/A",E5="N/A"),"N/A",ABS(C5-E5))
F30: =IF(OR(B5="N/A",D5="N/A"),"N/A",ABS(B5-D5)) | G30: =IF(OR(C5="N/A",E5="N/A"),"N/A",ABS(C5-E5))
F31: =IF(OR(B5="N/A",D5="N/A"),"N/A",ABS(B5-D5)) | G31: =IF(OR(C5="N/A",E5="N/A"),"N/A",ABS(C5-E5))
F32: =IF(OR(B5="N/A",D5="N/A"),"N/A",ABS(B5-D5)) | G32: =IF(OR(C5="N/A",E5="N/A"),"N/A",ABS(C5-E5))
F33: =IF(OR(B5="N/A",D5="N/A"),"N/A",ABS(B5-D5)) | G33: =IF(OR(C5="N/A",E5="N/A"),"N/A",ABS(C5-E5))
F34: =IF(OR(B5="N/A",D5="N/A"),"N/A",ABS(B5-D5)) | G34: =IF(OR(C5="N/A",E5="N/A"),"N/A",ABS(C5-E5))
F35: =IF(OR(B5="N/A",D5="N/A"),"N/A",ABS(B5-D5)) | G35: =IF(OR(C5="N/A",E5="N/A"),"N/A",ABS(C5-E5))
F36: =IF(OR(B5="N/A",D5="N/A"),"N/A",ABS(B5-D5)) | G36: =IF(OR(C5="N/A",E5="N/A"),"N/A",ABS(C5-E5))
F37: =IF(OR(B5="N/A",D5="N/A"),"N/A",ABS(B5-D5)) | G37: =IF(OR(C5="N/A",E5="N/A"),"N/A",ABS(C5-E5))
F38: =IF(OR(B5="N/A",D5="N/A"),"N/A",ABS(B5-D5)) | G38: =IF(OR(C5="N/A",E5="N/A"),"N/A",ABS(C5-E5))
F39: =IF(OR(B5="N/A",D5="N/A"),"N/A",ABS(B5-D5)) | G39: =IF(OR(C5="N/A",E5="N/A"),"N/A",ABS(C5-E5))
F40: =IF(OR(B5="N/A",D5="N/A"),"N/A",ABS(B5-D5)) | G40: =IF(OR(C5="N/A",E5="N/A"),"N/A",ABS(C5-E5))
F41: =IF(OR(B5="N/A",D5="N/A"),"N/A",ABS(B5-D5)) | G41: =IF(OR(C5="N/A",E5="N/A"),"N/A",ABS(C5-E5))
F42: =IF(OR(B5="N/A",D5="N/A"),"N/A",ABS(B5-D5)) | G42: =IF(OR(C5="N/A",E5="N/A"),"N/A",ABS(C5-E5))
F43: =IF(OR(B5="N/A",D5="N/A"),"N/A",ABS(B5-D5)) | G43: =IF(OR(C5="N/A",E5="N/A"),"N/A",ABS(C5-E5))
F44: =IF(OR(B5="N/A",D5="N/A"),"N/A",ABS(B5-D5)) | G44: =IF(OR(C5="N/A",E5="N/A"),"N/A",ABS(C5-E5))
F45: =IF(OR(B5="N/A",D5="N/A"),"N/A",ABS(B5-D5)) | G45: =IF(OR(C5="N/A",E5="N/A"),"N/A",ABS(C5-E5))
F46: =IF(OR(B5="N/A",D5="N/A"),"N/A",ABS(B5-D5)) | G46: =IF(OR(C5="N/A",E5="N/A"),"N/A",ABS(C5-E5))
F47: =IF(OR(B5="N/A",D5="N/A"),"N/A",ABS(B5-D5)) | G47: =IF(OR(C5="N/A",E5="N/A"),"N/A",ABS(C5-E5))
F48: =IF(OR(B5="N/A",D5="N/A"),"N/A",ABS(B5-D5)) | G48: =IF(OR(C5="N/A",E5="N/A"),"N/A",ABS(C5-E5))
F49: =IF(OR(B5="N/A",D5="N/A"),"N/A",ABS(B5-D5)) | G49: =IF(OR(C5="N/A",E5="N/A"),"N/A",ABS(C5-E5))
F50: =IF(OR(B5="N/A",D5="N/A"),"N/A",ABS(B5-D5)) | G50: =IF(OR(C5="N/A",E5="N/A"),"N/A",ABS(C5-E5))
F51: =IF(OR(B5="N/A",D5="N/A"),"N/A",ABS(B5-D5)) | G51: =IF(OR(C5="N/A",E5="N/A"),"N/A",ABS(C5-E5))
F52: =IF(OR(B5="N/A",D5="N/A"),"N/A",ABS(B5-D5)) | G52: =IF(OR(C5="N/A",E5="N/A"),"N/A",ABS(C5-E5))
F53: =IF(OR(B5="N/A",D5="N/A"),"N/A",ABS(B5-D5)) | G53: =IF(OR(C5="N/A",E5="N/A"),"N/A",ABS(C5-E5))
F54: =IF(OR(B5="N/A",D5="N/A"),"N/A",ABS(B5-D5)) | G54: =IF(OR(C5="N/A",E5="N/A"),"N/A",ABS(C5-E5))
F55: =IF(OR(B5="N/A",D5="N/A"),"N/A",ABS(B5-D5)) | G55: =IF(OR(C5="N/A",E5="N/A"),"N/A",ABS(C5-E5))
F56: =IF(OR(B5="N/A",D5="N/A"),"N/A",ABS(B5-D5)) | G56: =IF(OR(C5="N/A",E5="N/A"),"N/A",ABS(C5-E5))
F57: =IF(OR(B5="N/A",D5="N/A"),"N/A",ABS(B5-D5)) | G57: =IF(OR(C5="N/A",E5="N/A"),"N/A",ABS(C5-E5))
F58: =IF(OR(B5="N/A",D5="N/A"),"N/A",ABS(B5-D5)) | G58: =IF(OR(C5="N/A",E5="N/A"),"N/A",ABS(C5-E5))
F59: =IF(OR(B5="N/A",D5="N/A"),"N/A",ABS(B5-D5)) | G59: =IF(OR(C5="N/A",E5="N/A"),"N/A",ABS(C5-E5))
F60: =IF(OR(B5="N/A",D5="N/A"),"N/A",ABS(B5-D5)) | G60: =IF(OR(C5="N/A",E5="N/A"),"N/A",ABS(C5-E5))
F61: =IF(OR(B5="N/A",D5="N/A"),"N/A",ABS(B5-D5)) | G61: =IF(OR(C5="N/A",E5="N/A"),"N/A",ABS(C5-E5))
F62: =IF(OR(B5="N/A",D5="N/A"),"N/A",ABS(B5-D5)) | G62: =IF(OR(C5="N/A",E5="N/A"),"N/A",ABS(C5-E5))
F63: =IF(OR(B5="N/A",D5="N/A"),"N/A",ABS(B5-D5)) | G63: =IF(OR(C5="N/A",E5="N/A"),"N/A",ABS(C5-E5))
F64: =IF(OR(B5="N/A",D5="N/A"),"N/A",ABS(B5-D5)) | G64: =IF(OR(C5="N/A",E5="N/A"),"N/A",ABS(C5-E5))
F65: =IF(OR(B5="N/A",D5="N/A"),"N/A",ABS(B5-D5)) | G65: =IF(OR(C5="N/A",E5="N/A"),"N/A",ABS(C5-E5))
F66: =IF(OR(B5="N/A",D5="N/A"),"N/A",ABS(B5-D5)) | G66: =IF(OR(C5="N/A",E5="N/A"),"N/A",ABS(C5-E5))
F67: =IF(OR(B5="N/A",D5="N/A"),"N/A",ABS(B5-D5)) | G67: =IF(OR(C5="N/A",E5="N/A"),"N/A",ABS(C5-E5))
F68: =IF(OR(B5="N/A",D5="N/A"),"N/A",ABS(B5-D5)) | G68: =IF(OR(C5="N/A",E5="N/A"),"N/A",ABS(C5-E5))
F69: =IF(OR(B5="N/A",D5="N/A"),"N/A",ABS(B5-D5)) | G69: =IF(OR(C5="N/A",E5="N/A"),"N/A",ABS(C5-E5))
F70: =IF(OR(B5="N/A",D5="N/A"),"N/A",ABS(B5-D5)) | G70: =IF(OR(C5="N/A",E5="N/A"),"N/A",ABS(C5-E5))
F71: =IF(OR(B5="N/A",D5="N/A"),"N/A",ABS(B5-D5)) | G71: =IF(OR(C5="N/A",E5="N/A"),"N/A",ABS(C5-E5))
F72: =IF(OR(B5="N/A",D5="N/A"),"N/A",ABS(B5-D5)) | G72: =IF(OR(C5="N/A",E5="N/A"),"N/A",ABS(C5-E5))
F73: =IF(OR(B5="N/A",D5="N/A"),"N/A",ABS(B5-D5)) | G73: =IF(OR(C5="N/A",E5="N/A"),"N/A",ABS(C5-E5))
F74: =IF(OR(B5="N/A",D5="N/A"),"N/A",ABS(B5-D5)) | G74: =IF(OR(C5="N/A",E5="N/A"),"N/A",ABS(C5-E5))
F75: =IF(OR(B5="N/A",D5="N/A"),"N/A",ABS(B5-D5)) | G75: =IF(OR(C5="N/A",E5="N/A"),"N/A",ABS(C5-E5))
F76: =IF(OR(B5="N/A",D5="N/A"),"N/A",ABS(B5-D5)) | G76: =IF(OR(C5="N/A",E5="N/A"),"N/A",ABS(C5-E5))
F77: =IF(OR(B5="N/A",D5="N/A"),"N/A",ABS(B5-D5)) | G77: =IF(OR(C5="N/A",E5="N/A"),"N/A",ABS(C5-E5))
F78: =IF(OR(B5="N/A",D5="N/A"),"N/A",ABS(B5-D5)) | G78: =IF(OR(C5="N/A",E5="N/A"),"N/A",ABS(C5-E5))
F79: =IF(OR(B5="N/A",D5="N/A"),"N/A",ABS(B5-D5)) | G79: =IF(OR(C5="N/A",E5="N/A"),"N/A",ABS(C5-E5))
F80: =IF(OR(B5="N/A",D5="N/A"),"N/A",ABS(B5-D5)) | G80: =IF(OR(C5="N/A",E5="N/A"),"N/A",ABS(C5-E5))
F81: =IF(OR(B5="N/A",D5="N/A"),"N/A",ABS(B5-D5)) | G81: =IF(OR(C5="N/A",E5="N/A"),"N/A",ABS(C5-E5))
F82: =IF(OR(B5="N/A",D5="N/A"),"N/A",ABS(B5-D5)) | G82: =IF(OR(C5="N/A",E5="N/A"),"N/A",ABS(C5-E5))
F83: =IF(OR(B5="N/A",D5="N/A"),"N/A",ABS(B5-D5)) | G83: =IF(OR(C5="N/A",E5="N/A"),"N/A",ABS(C5-E5))
F84: =IF(OR(B5="N/A",D5="N/A"),"N/A",ABS(B5-D5)) | G84: =IF(OR(C5="N/A",E5="N/A"),"N/A",ABS(C5-E5))
F85: =IF(OR(B5="N/A",D5="N/A"),"N/A",ABS(B5-D5)) | G85: =IF(OR(C5="N/A",E5="N/A"),"N/A",ABS(C5-E5))
F86: =IF(OR(B5="N/A",D5="N/A"),"N/A",ABS(B5-D5)) | G86: =IF(OR(C5="N/A",E5="N/A"),"N/A",ABS(C5-E5))
F87: =IF(OR(B5="N/A",D5="N/A"),"N/A",ABS(B5-D5)) | G87: =IF(OR(C5="N/A",E5="N/A"),"N/A",ABS(C5-E5))
F88: =IF(OR(B5="N/A",D5="N/A"),"N/A",ABS(B5-D5)) | G88: =IF(OR(C5="N/A",E5="N/A"),"N/A",ABS(C5-E5))
F89: =IF(OR(B5="N/A",D5="N/A"),"N/A",ABS(B5-D5)) | G89: =IF(OR(C5="N/A",E5="N/A"),"N/A",ABS(C5-E5))
F90: =IF(OR(B5="N/A",D5="N/A"),"N/A",ABS(B5-D5)) | G90: =IF(OR(C5="N/A",E5="N/A"),"N/A",ABS(C5-E5))
F91: =IF(OR(B5="N/A",D5="N/A"),"N/A",ABS(B5-D5)) | G91: =IF(OR(C5="N/A",E5="N/A"),"N/A",ABS(C5-E5))
F92: =IF(OR(B5="N/A",D5="N/A"),"N/A",ABS(B5-D5)) | G92: =IF(OR(C5="N/A",E5="N/A"),"N/A",ABS(C5-E5))
F93: =IF(OR(B5="N/A",D5="N/A"),"N/A",ABS(B5-D5)) | G93: =IF(OR(C5="N/A",E5="N/A"),"N/A",ABS(C5-E5))
F94: =IF(OR(B5="N/A",D5="N/A"),"N/A",ABS(B5-D5)) | G94: =IF(OR(C5="N/A",E5="N/A"),"N/A",ABS(C5-E5))
F95: =IF(OR(B5="N/A",D5="N/A"),"N/A",ABS(B5-D5)) | G95: =IF(OR(C5="N/A",E5="N/A"),"N/A",ABS(C5-E5))
F96: =IF(OR(B5="N/A",D5="N/A"),"N/A",ABS(B5-D5)) | G96: =IF(OR(C5="N/A",E5="N/A"),"N/A",ABS(C5-E5))
F97: =IF(OR(B5="N/A",D5="N/A"),"N/A",ABS(B5-D5)) | G97: =IF(OR(C5="N/A",E5="N/A"),"N/A",ABS(C5-E5))
F98: =IF(OR(B5="N/A",D5="N/A"),"N/A",ABS(B5-D5)) | G98: =IF(OR(C5="N/A",E5="N/A"),"N/A",ABS(C5-E5))
F99: =IF(OR(B5="N/A",D5="N/A"),"N/A",ABS(B5-D5)) | G99: =IF(OR(C5="N/A",E5="N/A"),"N/A",ABS(C5-E5))
F100: =IF(OR(B5="N/A",D5="N/A"),"N/A",ABS(B5-D5)) | G100: =IF(OR(C5="N/A",E5="N/A"),"N/A",ABS(C5-E5))
...
